README.rst
setup.cfg
setup.py
ok/__init__.py
ok/keys.py
ok/tests/__init__.py
ok/tests/module_test.py
ok/tests/test_key.py
ok_redis.egg-info/PKG-INFO
ok_redis.egg-info/SOURCES.txt
ok_redis.egg-info/dependency_links.txt
ok_redis.egg-info/not-zip-safe
ok_redis.egg-info/requires.txt
ok_redis.egg-info/top_level.txt