Metadata-Version: 1.1
Name: ok-redis
Version: 0.1.2
Summary: Object-Key Mapper for Redis
Home-page: https://github.com/mixxorz/ok-redis
Author: Mitchel Cabuloy (mixxorz)
Author-email: mixxorz@gmail.com
License: MIT
Platform: UNKNOWN
Classifier: Development Status :: 4 - Beta
Classifier: Intended Audience :: Developers
Classifier: License :: OSI Approved :: MIT License
Classifier: Operating System :: OS Independent
Classifier: Programming Language :: Python :: 2.7
Classifier: Programming Language :: Python :: 3.4
Classifier: Programming Language :: Python :: 3.5
Classifier: Topic :: Database
Classifier: Topic :: Utilities
